{
  "ts": "2026-06-14 21:40",
  "records": [
    {
      "code": "SZ300866",
      "name": "安克创新",
      "w": 2.4,
      "a_code": "300866",
      "date": "2026-05-24",
      "title": "安克创新:2026年5月8日-5月22日投资者关系活动记录表",
      "art_code": "AN202605241822841249",
      "summary": "本次调研中，机构关注了安克创新的平台化能力、可穿戴设备在AI环境下的发展以及公司未来的技术布局。公司表示，通过三层研发架构提升技术成果转化效率，并实现核心能力的高效复用。针对可穿戴设备，安克强调当前主要提升感知能力，未来随着技术进步，端侧硬件的角色将逐步扩展。2025年，充电储能、智能创新和智能影音业务分别实现收入154.02亿元、82.71亿元和68.33亿元，均保持了良好的增长态势。",
      "fulltext": "证券代码：300866        证券简称：安克创新      公告编号：2026-003\r\n债券代码：123257        债券简称：安克转债\r\n\r\n                安克创新科技股份有限公司\r\n\r\n                  投资者关系活动记录表\r\n\r\n            特定对象调研      □分析师会议\r\n\r\n投资者关系活 □媒体采访          业绩说明会\r\n\r\n  动类别    □新闻发布会        路演活动\r\n\r\n            □现场参观          其他 线上会议等\r\n\r\n参与单位名称 线上 287 家机构共 385 位参会人员，线下 27 家机构共 55 位参\r\n            会人员，详见附件清单\r\n\r\n    时间    2026 年 5 月 8 日至 2026 年 5 月 22 日\r\n\r\n    地点    公司会议室、电话及网络会议\r\n\r\n            董事长：阳萌\r\n\r\n            董事、总经理：赵东平\r\n\r\n            董事：祝芳浩\r\n\r\n上市公司接待 董事：熊康\r\n\r\n  人员姓名\r\n\r\n            财务负责人：杨帆\r\n\r\n            董事会秘书：彭文婷\r\n\r\n            投资者关系负责人：张泽宇\r\n\r\n                环节：介绍公司 2025 年度经营情况、问答交流。\r\n\r\n                一、介绍公司 2025 年度经营情况\r\n\r\n 投资者关系\r\n\r\n                （一）战略介绍\r\n\r\n 活动主要内\r\n\r\n  容介绍        感谢各位股东、投资者对公司的支持和关注。战略层面，\r\n            公司持续聚焦“浅海”市场。这类市场通常具有一定技术共通\r\n            性，公司可通过持续研发投入、产品创新和全球化运营能力，\r\n            在多个品类中实现能力复用和业务拓展，并通过多品类布局构\r\n            建长期增长基础。多品类布局对公司的研发协同、组织管理和\r\n资源配置能力提出了更高要求，同时也有助于公司在不同用户场景中持续沉淀技术、品牌、渠道和供应链能力，推动业务规模和组织能力的长期演进。\r\n\r\n  在产品线方面，目前公司旗下产品涵盖充电储能、智能创新和智能影音三大板块。公司持续围绕不同用户在品质、功能和体验方面的差异化需求推进产品布局。公司将在巩固既有优势的同时，持续推动更多产品向更高品质、更优体验的方向升级。\r\n\r\n  在组织能力建设方面，公司持续推进数智化建设，积极探索 AI 工具在内部管理和业务流程中的应用。目前，公司已在品牌营销、客户服务、产品设计支持等多个场景引入 AI 辅助工具，并将部分可标准化的业务流程和经验沉淀为可复用工具，以提升内部协同效率和运营管理能力。同时，公司持续推进更加敏捷的小型团队机制，通过工具化、流程化的方式提升跨团队协作效率，更好支持业务快速响应和持续创新。\r\n\r\n  总体来看，公司将继续围绕核心能力建设、产品创新和全球化布局，推动各业务板块的协同发展，持续提升经营质量和长期竞争力。\r\n\r\n  （二）业务介绍\r\n\r\n  1、充电储能类\r\n\r\n  2025 年，公司充电储能类业务实现收入 154.02 亿元，同\r\n比增长 21.59%，占总营收的比例为 50.47%。\r\n\r\n  在移动充电领域，公司持续围绕高功率、大容量、多接口等用户需求推进产品迭代，通过中高端产品系列的持续升级，进一步提升了该品类的市场竞争力和品牌影响力。\r\n\r\n  在消费级储能领域，公司便携式移动储能、阳台光伏储能及户用储能等方向均保持了较好的发展态势。2025 年公司储能业务收入超过 45 亿元，主要来自便携式移动储能和阳台光伏储能两大产品线。其中，阳台光伏储能产品持续获得市场积极\r\n反馈，Anker SOLIX Solarbank 3 E2700 Pro 将微型逆变器、BMS\r\n及电池集成于单个单元，进一步降低了安装复杂度的同时，也改善了传统户储产品成本较高、安装繁琐及回本周期较长等痛\r\n点。\r\n\r\n  未来，公司也将围绕家庭发电、储电、用电及充电等场景，持续推进产品创新和本地化布局。\r\n\r\n  2、智能创新类\r\n\r\n  2025 年，公司智能创新类业务实现收入 82.71 亿元，同比\r\n增长 30.53%，占总营收的比例为 27.11%。\r\n\r\n  智能安防领域，公司继续坚持“本地安全”的差异化定位，支持用户影像数据存储于本地设备，以提升隐私保护体验。随着 AI 大模型与边缘计算技术的发展，公司也在积极探索本地 AI 安防管家（Local AI Agent）等方向的应用。产品品类不断丰富，覆盖不同使用场景，整体保持了较好的市场反馈。\r\n\r\n  智能清洁领域，公司聚焦用户核心需求，持续优化产品能力和用户体验。扫地机器人等相关产品在技术积累和产品力提升方面取得进展，产品竞争力和品牌认知度持续提升。\r\n\r\n  智能母婴领域，热敷穿戴吸奶器 S1 Pro 已面向全球市场销\r\n售，并于 2025 年 7 月在中国大陆地区上市。母婴业务于报告期内实现了较好增长，已形成一定规模的营收贡献。\r\n\r\n  创意打印领域，eufyMake UV Printer E1 于 2025 年 4 月上\r\n线 Kickstarter 众筹平台，众筹金额超过 4,600 万美元，并获得较高市场关注。未来，公司将结合产品规划、能力积累和市场机会，持续聚焦 UV 打印方向推进产品迭代和业务拓展。\r\n\r\n  整体来看，智能创新类业务围绕家庭智能化应用场景，持续在安防、清洁、母婴及创意打印等方向推进产品迭代和品类拓展，相关业务在重点区域市场保持了较好的发展态势。\r\n\r\n  3、智能影音类\r\n\r\n  2025 年，公司智能影音类业务实现收入 68.33 亿元，同比\r\n增长 20.05%，占总营收的比例为 22.39%。\r\n\r\n  在智能音频领域，公司围绕消费者对音质、降噪、场景适配和产品外观设计等方面的需求，持续推出多款创新产品，涵\r\n盖 TWS 降噪耳机、头戴式降噪耳机、运动耳机及音箱等方向。睡眠耳机产品则围绕鼾声遮蔽、助眠音频等方向，持续探索细分场景下的差异化体验。\r\n\r\n  在智能投影领域，公司持续推进影音一体化战略，优化投影仪等产品线，面向不同使用场景推出便携影音、户外影音等系列产品，并结合用户需求推进产品迭代。\r\n\r\n  公司于 2026 年 4 月发布了首款神经网络存算一体 AI 音频\r\n芯片 Thus™。Thus™芯片基于 NOR Flash 技术打造，原生支持4 兆参数模型，为公司首款神经网络存算一体 AI 音频芯片。根据内部实验室测试结果，Thus™较传统蓝牙耳机芯片可实现最高 150 倍 AI 峰值算力提升，可支持端到端神经网络在端侧设备运行，并实现兆级模型在耳机端部署。该芯片会率先搭载于公司旗舰耳机产品。\r\n\r\n  整体来看，智能影音类业务保持了稳步发展态势。未来公司将持续在声学算法、影像显示技术等方向加大研发投入，通过产品力、品牌力和渠道能力的协同提升，进一步增强市场竞争力。\r\n\r\n  二、问答交流\r\n\r\n  Q1：公司平台化能力具体体现在哪些方面？\r\n\r\n  A：您好，公司始终坚持以技术创新驱动产品迭代与品类拓展，持续完善由研发实验室、领域技术平台和产品交付团队构成的三层研发架构，覆盖前沿研究、共性技术沉淀及产品开发与市场落地等关键环节，不断提升技术成果转化效率和跨品类复用能力。在此基础上，公司通过统一的研发框架与协同机制，实现核心能力在不同产品线间的高效复用，支持新品类的快速验证与规模化落地。\r\n\r\n  Q2：可穿戴设备（如耳机）在 AI 环境下的发展节奏如何？\r\n\r\n  A：您好，从当前技术条件来看，复杂模型的推理对算力和功耗要求较高，更适合部署在手机等计算资源更充裕的终端\r\n设备上；而耳机等可穿戴设备在体积、散热和续航方面受限，现阶段更适宜承担感知类任务，如声音采集、环境识别等。基于这一判断，公司当前的策略是优先提升端侧设备的感知能力，例如通过自研芯片优化耳机的通话降噪体验。当然，随着端侧模型小型化、低功耗技术的持续进步，端侧硬件在 AI 生态中的角色有望逐步扩展。\r\n\r\n  Q3：公司在外部人才引进和内部人才梯队培养方面有哪些举措？\r\n\r\n  A：您好，公司坚持“内部培养+外部引进”的双轨机制：一方面通过校招持续注入新鲜血液，夯实长期人才基础；另一方面，在关键技术或重大项目领域，公司会根据业务发展需要，在全球范围内引进优秀专业人才。这种机制既确保组织的延续性与文化传承，又为突破性创新提供关键人才支撑，是支撑公司长期发展的重要基础。\r\n\r\n  Q4：充电类市场的增长来源是什么？增长来自市场扩容还是份额提升？\r\n\r\n  A：您好，综合来看，增长来源于两者的叠加。第一，全球充电市场仍处于稳健增长通道，智能终端设备数量持续增加、功耗上升，驱动了用户对多场景补能方案的需求。第二，公司在该市场中的份额也实现了有效提升。例如，公司推出了适用于笔记本电脑充电等场景的高功率移动电源产品——Anker 能量舱移动电源，该产品开辟了新的细分应用场景。公司通过产品创新不仅扩大了品类的潜在市场边界，也进一步提升了公司竞争力。\r\n\r\n  Q5：公司储能业务目前的产品布局和未来发展思路如何？\r\n  A：您好，从整体储能业务来看，公司目前已形成便携式移动储能、阳台光伏储能和户用储能等多元化产品布局。整体来看，储能市场需求保持增长，公司在相关产品、品牌、渠道和服务体系方面持续积累竞争优势，主要体现在对用户场景的深刻理解、持续提升的技术和产品创新能力，以及品牌、渠道\r\n和服务体系的综合优势。未来，公司会继续围绕用户真实需求，持续提升储能业务的整体竞争力。\r\n\r\n  Q6：公司在具身智能方向的研发进展如何？\r\n\r\n  A：您好，公司在具身智能方向的研发正按规划稳步推进。当前，公司在二维基础型机器人（如扫地机）领域已形成稳定的商业化规模，并在持续迭代用户体验；同时，公司已启动三维移动型机器人（如机器狗）的技术研发和产品规划；三维交互型人形/类人形机器人，公司正在搭建底层技术栈和系统化平台，逐步夯实长期能力储备。\r\n\r\n  Q7：公司的母婴品类发展如何？\r\n\r\n  A：您好，母婴品类是公司重点关注的业务方向之一。公司旗下母婴产品线已在逐步拓展，覆盖从吸乳、储存、加热到清洗、消毒、烘干的全线场景，致力于为用户提供完整且良好的使用体验。从运营结果看，相关产品获得了较好的用户反馈，体现了用户对产品品质和功能设计的认可。未来，公司将继续围绕用户需求深化产品布局，持续提升在母婴市场中的竞争力。\r\n\r\n  Q8：公司储能业务的增长情况如何？如何看待阳台光伏储能领域的需求趋势？\r\n\r\n  A：您好，2025 年公司整体储能业务收入超过 45 亿元，\r\n主要增长来自便携式移动储能和阳台光伏储能两大产品线。从需求趋势看，阳台光储的核心驱动仍然来自用户降低能源成本、提升用电灵活性、改善产品回本周期以及降低安装复杂度的需求。\r\n\r\n  Q9：公司在北美储能市场布局策略是怎么样的？\r\n\r\n  A：您好，美国市场是公司储能业务的重要市场之一。当前北美家庭用户在应急备电、户外用电、部分家庭用电备份等场景中存在较多需求。同时，随着清洁能源政策推进和储能产\r\n\r\n          品性价比的提升，这部分传统设备在未来可能逐步面临更新替\r\n          代的长期需求，为公司储能业务提供了潜在的增长空间。\r\n\r\n              目前，公司已在美国市场推出多款储能产品，覆盖不同层\r\n          级的备电需求，并将持续围绕用户场景推进产品创新与本地化\r\n          运营。在商业模式上，公司重视直接触达用户和本地化服务能\r\n          力建设，并将根据不同产品形态和"
    },
    {
      "code": "SZ300750",
      "name": "宁德时代",
      "w": 1.2,
      "a_code": "300750",
      "date": "2026-04-16",
      "title": "宁德时代:2026年4月15日投资者关系活动记录表",
      "art_code": "AN202604161821252967",
      "summary": "在2026年第一季度业绩说明会上，宁德时代报告总营收1,291亿元和净利润207亿元，分别同比增长52.5%和48.5%。公司动力和储能业务销量超过200GWh，储能占比提升至25%。针对中东地缘冲突，公司认为短期内会促使消费者倾向电动化产品。公司将于4月21日举办“超级科技日”，推出新技术和产品。此外，因锂、镍等资源需求旺盛，公司设立时代资源集团以保障上游原材料供应。",
      "fulltext": "证券代码：300750                                  证券简称：宁德时代\r\n          宁德时代新能源科技股份有限公司\r\n\r\n              投资者关系活动记录表\r\n\r\n                                                      编号：2026-002\r\n\r\n                □特定对象调研        □分析师会议\r\n\r\n                □媒体采访            ■业绩说明会\r\n\r\n 投资者关系活\r\n\r\n                □新闻发布会          □路演活动\r\n\r\n 动类别\r\n\r\n                □现场参观\r\n\r\n                □其他\r\n\r\n 参与单位名称\r\n\r\n                与会投资者约 1,470 人\r\n\r\n 及人员姓名\r\n\r\n 时间          2026 年 4 月 15 日\r\n\r\n 地点          电话会议\r\n\r\n 上市公司接待 董事会秘书兼副总经理 蒋理\r\n\r\n                财务总监 郑舒\r\n\r\n 人员姓名      董事会办公室主任 林美娜\r\n\r\n                一、公司经营情况介绍\r\n\r\n                    2026 年第一季度，公司实现总营收 1,291亿元，同比增\r\n                长 52.5%；归属于上市公司股东的净利润 207 亿元，同比增\r\n                长 48.5%；公司现金储备充裕，期末货币资金及交易性金融\r\n 投资者关系活 资产合计超 4,100 亿元，有力支持高强度研发投入和全球产 动主要内容介 能建设。\r\n 绍\r\n\r\n                二、问答环节\r\n\r\n                    1、请问公司一季度动力和储能业务的占比情况？\r\n\r\n                    2026 年第一季度，动力和储能合计销量超过 200GWh，\r\n                其中，储能占比约 25%，较之前季度有明显提升，动力占比\r\n\r\n约 75%。\r\n\r\n    2、中东地缘冲突对公司动力和储能订单的影响？\r\n\r\n  在世界和平的大环境下，商业发展才会更顺利。地缘冲突已对全球宏观经济和供应链造成较大影响。长期来看，这会加速全球向新能源转型；短期而言，原油供应和油价的不确定性增加，会使得消费者更倾向于使用电动化产品。\r\n\r\n    3、听说公司将于 4 月 21 日举办“超级科技日”，请问\r\n届时会发布什么新技术和新产品？\r\n\r\n  公司将于 4 月 21 日举办 2026 年“超级科技日”，主题\r\n为“极域之约”。这将是公司成立以来技术密度最高的一场发布会。届时推出全新的技术、产品和生态，都将直击行业最关注的痛点。\r\n\r\n    4、注意到公司今明两年有较大幅度的扩产，想请教公司扩产是基于对行业 3-5 年中期维度怎样的判断？\r\n\r\n  公司在业内率先捕捉到市场需求增长，自 2024 年逐步启动扩产，2025-2026 年进一步提速。扩产主要受动力和储能领域的旺盛需求驱动。\r\n\r\n  动力电池领域，中国乘用车电动化渗透率已突破 50%，同时单车带电量持续提升，双重因素带动电池需求快速增长。商用动力电池也快速增长，国内市场出货量 2025 年同比翻倍以上增长。商用车作为生产力工具，一旦达到经济性拐点将加速扩张。\r\n\r\n  储能领域，随着国内 136 号文、114 号文落地，储能的\r\n市场定位和容量电价机制愈发清晰，已成为具备稳定收益的资产，带来国内需求爆发。海外方面，市场本身已具备明确的经济性，AI 和数据中心进一步带动了储能需求增长。\r\n\r\n\r\n  上述多个因素叠加，电动化与算电协同的趋势愈发明显。公司看到了明确的增量需求，因而持续推进扩产，抢抓市场机遇。\r\n\r\n    5、公司设立时代资源集团，注册资本达 300 亿，出于\r\n什么考量？\r\n\r\n  长期来看，动力和储能市场空间巨大，对锂、镍、铜、铝等金属资源需求旺盛。当前全球供应链不稳定性上升，为保障上游原材料供应安全及稳定，公司已逐步布局相关矿产资源。\r\n\r\n  为进一步优化公司业务布局，保障供应链安全与稳定，根据公司整体发展战略规划，公司拟投资设立全资子公司时代资源集团，该子公司将定位为公司新能源矿产领域的专业投资运营与管理平台。\r\n\r\n    6、一季度公司动力电池出货增长较快，但国内乘用车行业销量好像是下滑的，背后的驱动因素是什么？\r\n\r\n  一方面，是因为公司乘用车市场份额提升：根据中国动力电池联盟数据，2026 年第一季度公司国内动力电池装机市占率为 47.7%，同比增加 3.4pct；另一方面，是由于单车带电量有一定提升。上述两因素叠加，带动公司一季度动力电池出货量实现较快增长。\r\n\r\n    7、公司一季度毛利率略有下降的原因？\r\n\r\n  一方面是受到原材料上涨（如碳酸锂及大宗商品）影响。对此，公司正通过完善供应链布局、规模效应、产品设计优化、大单品策略等措施进行对冲。另一方面是因为产品机构的变化，尤其国内储能出货量快速增长，使得储能占比明显提升。\r\n\r\n    8、看到很多车企的出口版车型都使用宁德时代的电\r\n\r\n\r\n              池，想了解公司在出口领域的市占率情况？\r\n\r\n                  公司电池产品在品质、性能等方面具有市场竞争力，\r\n              受到出口车企的青睐。\r\n\r\n                  9、出口退税退坡的影响？匈牙利工厂成本与国内相比\r\n              怎样？\r\n\r\n                  4 月 1 日起出口退税率下调对公司整体影响较小。\r\n\r\n                  匈牙利工厂当前成本虽较国内稍高，但相比德国工厂\r\n              有明显优势，目前正在产能爬坡阶段。公司将通过产线和\r\n              设备选型优化、简化电芯品类等方式提高生产效率及降低\r\n              成本。\r\n\r\n                  10、一季度公允价值变动较大的原因？\r\n\r\n                  主要来自于理财规模的扩大。当前存款收益率较低，\r\n              公司在年度股东大会上获得提升理财额度的相关授权，将\r\n              部分存款资金转为理财产品。\r\n\r\n附件清单\r\n\r\n              无\r\n\r\n（如有）\r\n\r\n日期          2026 年 4 月 15 日"
    },
    {
      "code": "SZ300014",
      "name": "亿纬锂能",
      "w": 1.2,
      "a_code": "300014",
      "date": "",
      "title": "",
      "art_code": "",
      "summary": "暂无投资者关系活动记录",
      "fulltext": ""
    },
    {
      "code": "HK02899",
      "name": "紫金矿业",
      "w": 1.1,
      "a_code": "601899",
      "date": "",
      "title": "",
      "art_code": "",
      "summary": "暂无投资者关系活动记录",
      "fulltext": ""
    },
    {
      "code": "SH603308",
      "name": "应流股份",
      "w": 1,
      "a_code": "603308",
      "date": "",
      "title": "",
      "art_code": "",
      "summary": "暂无投资者关系活动记录",
      "fulltext": ""
    },
    {
      "code": "HK01211",
      "name": "比亚迪",
      "w": 1,
      "a_code": "002594",
      "date": "2026-06-10",
      "title": "比亚迪:2026年6月9日投资者关系活动记录表",
      "art_code": "AN202606101823425856",
      "summary": "在比亚迪的投资者关系活动中，机构关注了智能化竞争、海外发展、品牌高端化、插混技术战略及未来发展规划等问题。公司表示，已在智能驾驶领域做好全方位准备，拥有强大的数据支持；在海外市场通过本地化建厂实现可持续发展；将继续注重产品质量与技术创新，以提升品牌形象；插混技术将持续深耕，并推出新产品；未来五年将依靠技术创新和双轮驱动，力争在2030年前实现显著增长。",
      "fulltext": "证券代码：002594                        证券简称：比亚迪\r\n\r\n                        比亚迪股份有限公司\r\n\r\n                        投资者关系活动记录表\r\n\r\n                                                    编号：2026-09\r\n\r\n投资者关系 □特定对象调研      □分析师会议\r\n\r\n活动类别    □媒体采访            □业绩说明会\r\n\r\n            □新闻发布会          □路演活动\r\n\r\n            □现场参观\r\n\r\n            ☑其他 （2025 年度股东会&高管面对面交流会）\r\n\r\n参与单位名 受邀投资人逾千人\r\n称及人员姓\r\n名\r\n\r\n时间        2026-06-09\r\n\r\n地点        比亚迪六角大楼\r\n\r\n上市公司接 集团董事长兼总裁王传福，董事副董事长吕向阳，董事夏佐全，待人员姓名  独立董事蔡洪平，独立董事张敏，独立董事喻玲，高级副总裁兼\r\n            财务总监周亚琳，高级副总裁兼汽车新技术研究院院长杨冬生，\r\n            董事会秘书兼公司秘书李黔\r\n\r\n            公司介绍：\r\n\r\n                今年宏观经济面临压力，居民消费疲软，社零增速从 2025\r\n            年全年 3.7%放缓至 2026 年 1-4 月份的 1.9%。中国汽车行业“内\r\n投资者关系 冷外热”，根据中汽协会数据，2026 年前 4 个月，乘用车累计\r\n活动主要内 销量 806.3 万辆，同比-6.7%，出口 271.6 万辆，同比+68.8%，\r\n容介绍      剔除出口国内乘用车累计销量 534.7 万辆，同比-24%。新能源汽\r\n            车方面，受 2026 年起新能源汽车购置税政策调整以及去年年底\r\n            提前集中购车等因素影响，短期内国内新能源乘用车渗透率从去\r\n            年 12 月的 58.5%降至今年 1 月的 41.7%，2 月渗透率 46.8%小幅\r\n回升，也导致公司前两个月销量承压。3 月市场逐步回暖叠加油价上行，以及公司闪充技术发布后，4 月国内新能源乘用车渗透率 61.4%，创单月新高。\r\n\r\n  3 月份公司第二代刀片电池及闪充技术推出之后，订单出现爆发式的增长，目前产能供不应求，公司努力提升第二代刀片电池产能，从而满足强劲的订单需求，公司坚定认可电动化的领先优势。下半场智能化公司推出了泊车城区双兜底战略，发布首款4nm 璇玑 A3 芯片，引领行业智能化发展。海外来看，2025 年公司海外销售 105 万辆，2026 年有信心实现甚至超过原先的销量目标，在主流市场如欧洲、亚太、美洲、中东等地区销量表现都十分亮眼。随着产能稳步提升，明年第二代刀片电池产能释放后，国内、国际市场将同时发力，闪充生态也会落地全球，惠及全球用户。感谢各位股东对公司的一直以来的陪伴与支持，也感谢各位股东提出了很多好的反馈建议，公司将持续努力，以技术创新引领行业发展，回馈广大股东的支持。\r\n问题一：目前行业在智能化赛道竞争激烈，比亚迪坐拥海量行驶数据等核心优势，要如何发挥优势？L3 级自动驾驶的落地还需要多久？\r\n答：近几年人工智能的发展速度远超预期，汽车既是 AI 的受益者，也是重要参与者。公司提出了整车智能就是具身智能，率先推出全民智驾，希望让 AI 技术在汽车上快速落地。比亚迪在智能驾驶有 5,000 名工程师，团队也在全力探索，将 AI 技术落地到汽车领域。目前比亚迪辅助驾驶车型保有量车辆超 315 万台，每日生成超 2 亿公里数据，为公司研发更高阶智能驾驶提供很好的基础。针对 L3 级自动驾驶，比亚迪已经做好了全方位准备：芯片、算法、数据和生态均已布局。同时在欧洲、南美、东南亚、中东等地搭建全球驾驶训练中心。一旦法规落地，公司将快速的去推进。\r\n\r\n问题二：公司如何在海外构建长期稳定的发展格局，实现可持续出海？\r\n答：比亚迪以长期主义在海外深耕几十年，品牌、技术、产品、服务网络等都赢得海外市场认可。公司通过在本地化建厂，带动本土供应链发展、创造就业岗位、贡献税收，和当地市场形成多方共赢。公司出海战略目前已形成“拉美领跑、欧洲突破、亚太多点开花”的格局，在主流市场如欧洲、亚太、美洲、中东等地区销量表现都十分亮眼。\r\n问题三：公司如何加强高端化品牌的设计、营销等？\r\n答：汽车是关乎人身安全的交通工具，产品最终要回归本质。公司不会过度追求营销噱头，而是脚踏实地打磨产品、技术创新，只有过硬的产品实力，才能真正获得中高端用户的认可和信赖。比亚迪每年投入大量研发费用，吸纳顶尖人才，搭建完善的研发平台与应用场景，公司有信心能做出更好的技术，成为全球最好的公司之一。在设计方面，近期热销的钛 7 等车型，凭借出色的设计收获市场认可，公司也意识到产品设计、营销策划是非常重要的创新，未来公司会推出更多好的产品，补齐软实力，让硬核技术的价值实力进一步释放。各位股东提出的所有建议，管理层都会逐条梳理、认真研究。公司会用心打磨产品、优化体验，用更好的产品和经营业绩，回馈大家的支持与厚爱。\r\n问题四：闪充技术推出之后，未来插混技术在集团技术路线中的战略地位如何？\r\n答：插混技术是比亚迪从 2008 年开始到现在已经第五代，公司还在持续深耕，电机与电控技术和纯电是共通的。2026 年，我们也发布了长续航插混以及闪充插混的产品。此外，在海外市场公司也在持续投入，提升 DM-i 在中国和全球的应用，满足全球\r\n\r\n            广大消费者的用车需求。\r\n\r\n            问题五：未来 5-10 年公司发展规划？\r\n\r\n            答：当下汽车行业正迎来百年未有之大变局，比亚迪也是这场变\r\n            革的参与者与引领者。2020 年到 2025 年，公司年销量从 40 多\r\n            万辆增长至 460 万辆，增长势头强劲。未来公司将持续地技术创\r\n            新发展，在十五五首年，公司推出第二代刀片电池、闪充、璇玑\r\n            A3 芯片等技术，未来还有更多新的技术，希望国内国外双轮驱\r\n            动，让中国技术走向全球，相信在 2030 年会获得很大增长。\r\n            问题六：股东如何与公司共同发展，未来公司在市值管理上有哪\r\n            些措施？\r\n\r\n            答：各位股东讲了很多，公司的潜力大家都很认同，感谢各位股\r\n            东的支持。公司坚定长期主义，从 30 年前的 20 人团队逐步成长\r\n            到如今的规模，始终秉承技术创新的发展理念，跟随国家的战略\r\n            逐步成长，并且走向全球。今年第一季度新能源汽车渗透率比较\r\n            低，现在已经逐月恢复，公司 5 月销量也已经同比转正。随着第\r\n            二代刀片电池产能提升，销量将会进一步提升。海外表现也非常\r\n            好，海外除了比亚迪品牌外，高端品牌也在持续出海。比亚迪在\r\n            未来的发展当中，会把握各个节点，科学前瞻地布局，不放过任\r\n            何一个重大的技术变革，实现公司更好的发展，也实现更好的股\r\n            东回报。\r\n\r\n附 件 清 单 无\r\n（如有）\r\n\r\n日期        2026-6-9"
    },
    {
      "code": "HK09626",
      "name": "哔哩哔哩",
      "w": 1,
      "a_code": "09626",
      "date": "",
      "title": "",
      "art_code": "",
      "summary": "暂无投资者关系活动记录",
      "fulltext": ""
    },
    {
      "code": "SZ001309",
      "name": "德明利",
      "w": 0.9,
      "a_code": "001309",
      "date": "",
      "title": "",
      "art_code": "",
      "summary": "暂无投资者关系活动记录",
      "fulltext": ""
    }
  ]
}