{
  "ts": "2026-06-15 20:49",
  "list": [
    {
      "rank": 1,
      "symbol": "SZ300014",
      "name": "亿纬锂能",
      "current": 58.77,
      "percent": 1.91,
      "value": 13410.0,
      "chg": 1.1
    },
    {
      "rank": 2,
      "symbol": "SZ300308",
      "name": "中际旭创",
      "current": 1245.0,
      "percent": 8.36,
      "value": 6932.0,
      "chg": 96.0
    },
    {
      "rank": 3,
      "symbol": "SZ301217",
      "name": "铜冠铜箔",
      "current": 170.16,
      "percent": 20.0,
      "value": 5856.0,
      "chg": 28.36
    },
    {
      "rank": 4,
      "symbol": "SZ002851",
      "name": "麦格米特",
      "current": 148.76,
      "percent": 10.0,
      "value": 4928.0,
      "chg": 13.52
    },
    {
      "rank": 5,
      "symbol": "SZ002384",
      "name": "东山精密",
      "current": 239.31,
      "percent": 10.0,
      "value": 4710.0,
      "chg": 21.76
    },
    {
      "rank": 6,
      "symbol": "SH688146",
      "name": "中船特气",
      "current": 318.3,
      "percent": 5.4,
      "value": 4272.0,
      "chg": 16.3
    },
    {
      "rank": 7,
      "symbol": "SH601899",
      "name": "紫金矿业",
      "current": 31.31,
      "percent": 7.63,
      "value": 3835.0,
      "chg": 2.22
    },
    {
      "rank": 8,
      "symbol": "SH600183",
      "name": "生益科技",
      "current": 166.41,
      "percent": 10.0,
      "value": 3488.0,
      "chg": 15.13
    },
    {
      "rank": 9,
      "symbol": "SZ000725",
      "name": "京东方A",
      "current": 5.92,
      "percent": 6.28,
      "value": 3054.0,
      "chg": 0.35
    },
    {
      "rank": 10,
      "symbol": "SZ300476",
      "name": "胜宏科技",
      "current": 344.5,
      "percent": 5.28,
      "value": 2979.0,
      "chg": 17.29
    },
    {
      "rank": 11,
      "symbol": "SZ002428",
      "name": "云南锗业",
      "current": 101.49,
      "percent": 10.0,
      "value": 2727.0,
      "chg": 9.23
    },
    {
      "rank": 12,
      "symbol": "SZ001399",
      "name": "惠科股份",
      "current": null,
      "percent": null,
      "value": 2672.0,
      "chg": null
    },
    {
      "rank": 13,
      "symbol": "SZ002636",
      "name": "金安国纪",
      "current": 97.34,
      "percent": 8.3,
      "value": 2654.0,
      "chg": 7.46
    },
    {
      "rank": 14,
      "symbol": "SH688143",
      "name": "长盈通",
      "current": 189.2,
      "percent": 5.7,
      "value": 2450.0,
      "chg": 10.2
    },
    {
      "rank": 15,
      "symbol": "SH603986",
      "name": "兆易创新",
      "current": 518.0,
      "percent": 7.59,
      "value": 2378.0,
      "chg": 36.53
    },
    {
      "rank": 16,
      "symbol": "SZ300620",
      "name": "光库科技",
      "current": 343.05,
      "percent": 20.0,
      "value": 2314.0,
      "chg": 57.17
    },
    {
      "rank": 17,
      "symbol": "SH601872",
      "name": "招商轮船",
      "current": 17.16,
      "percent": 10.0,
      "value": 2312.0,
      "chg": 1.56
    },
    {
      "rank": 18,
      "symbol": "SH688766",
      "name": "普冉股份",
      "current": 457.0,
      "percent": 17.0,
      "value": 2298.0,
      "chg": 66.41
    },
    {
      "rank": 19,
      "symbol": "SH600519",
      "name": "贵州茅台",
      "current": 1271.1,
      "percent": -1.61,
      "value": 2232.0,
      "chg": -20.81
    },
    {
      "rank": 20,
      "symbol": "SZ000636",
      "name": "风华高科",
      "current": 65.03,
      "percent": 10.0,
      "value": 2187.0,
      "chg": 5.91
    }
  ]
}